printables_stats/__init__.py
printables_stats/__main__.py
printables_stats/client.py
printables_stats-0.1.2.dist-info/METADATA
printables_stats-0.1.2.dist-info/WHEEL
printables_stats-0.1.2.dist-info/licenses/LICENSE
printables_stats-0.1.2.dist-info/RECORD
