Metadata-Version: 2.4
Name: printables-stats
Version: 0.1.2
Summary: Python library and CLI tool to scrape public user statistics from Printables.com
Project-URL: Homepage, https://gitlab.com/intheflow/printables-stats
Project-URL: Repository, https://gitlab.com/intheflow/printables-stats
Project-URL: Issues, https://gitlab.com/intheflow/printables-stats/-/issues
Author-email: Florian Schweikert <pypi@ist-total.org>
License: GPL-3.0
License-File: LICENSE
Keywords: 3d-printing,badges,printables,scraper,statistics
Classifier: Development Status :: 3 - Alpha
Classifier: Intended Audience :: Developers
Classifier: License :: OSI Approved :: GNU General Public License v3 (GPLv3)
Classifier: Programming Language :: Python :: 3
Classifier: Programming Language :: Python :: 3.14
Classifier: Topic :: Internet :: WWW/HTTP :: Dynamic Content
Classifier: Topic :: Software Development :: Libraries :: Python Modules
Requires-Python: >=3.11
Requires-Dist: beautifulsoup4>=4.14.3
Requires-Dist: requests>=2.32.5
